lmdbsystem/__init__.py
lmdbsystem/dataloader.py
lmdbsystem/error.py
lmdbsystem/lmdb.py
lmdbsystem/read_adapters/__init__.py
lmdbsystem/read_adapters/bytes_image.py
lmdbsystem/read_adapters/cv2_image.py
lmdbsystem/read_adapters/pil_image.py
lmdbsystem/read_adapters/text.py
lmdbsystem/write_adapters/__init__.py
lmdbsystem/write_adapters/image.py
lmdbsystem/write_adapters/text.py
lmdbsystem-0.2.2.dist-info/LICENSE.txt
lmdbsystem-0.2.2.dist-info/METADATA
lmdbsystem-0.2.2.dist-info/WHEEL
lmdbsystem-0.2.2.dist-info/top_level.txt
lmdbsystem-0.2.2.dist-info/RECORD
