Metadata-Version: 2.1
Name: lmdbsystem
Version: 0.2.2
Summary: Abstraction for read and write to the lmdb file
Author-email: Dao Quang Duy <duydaoquang12@gmail.com>
Maintainer-email: Rabiloo Developers <oss@rabiloo.com>
License: The MIT License
Project-URL: Homepage, https://github.com/rabiloo/python-lmdbsystem
Project-URL: Repository, https://github.com/rabiloo/python-lmdbsystem
Project-URL: Bug Tracker, https://github.com/rabiloo/python-lmdbsystem/issues
Keywords: lmdbsystem,lmdb
Classifier: Programming Language :: Python :: 3
Classifier: License :: OSI Approved :: MIT License
Classifier: Operating System :: OS Independent
Classifier: Development Status :: 2 - Pre-Alpha
Requires-Python: >=3.10
License-File: LICENSE.txt
Requires-Dist: lmdb
Requires-Dist: datas-helper[image]
Requires-Dist: tqdm
Provides-Extra: dev
Requires-Dist: black ; extra == 'dev'
Requires-Dist: flake8 ; extra == 'dev'
Requires-Dist: flake8-pyproject ; extra == 'dev'
Requires-Dist: pytest ; extra == 'dev'
Requires-Dist: pytest-asyncio ; extra == 'dev'
Requires-Dist: typing-extensions ; extra == 'dev'
Requires-Dist: isort ; extra == 'dev'
